PyBayfile/__init__.py
PyBayfile-1.0.dist-info/METADATA
PyBayfile-1.0.dist-info/WHEEL
PyBayfile-1.0.dist-info/top_level.txt
PyBayfile-1.0.dist-info/RECORD
