Metadata-Version: 2.1
Name: PyBayfile
Version: 1.0
Summary: Module to integrate bayfiles and control them in your code
Home-page: https://github.com/CSM-BlueRed/PyBayfile
Author: BlueRed
License: UNKNOWN
Keywords: python,files,api,web,bayfile
Platform: UNKNOWN
Classifier: Programming Language :: Python :: 3
Classifier: License :: OSI Approved :: MIT License
Requires-Python: >=3.6
Requires-Dist: aiohttp
